orm_core/__init__.py
orm_core/base.py
orm_core/base_schemes.py
orm_core/core_db.py
orm_core/orm_factory.py
orm_core/py.typed
orm_core/api/__init__.py
orm_core/api/api_model.py
orm_core/api/api_schemes.py
orm_core/api/basic_api.py
orm_core/basic_operations/__init__.py
orm_core/basic_operations/model/__init__.py
orm_core/basic_operations/model/add.py
orm_core/basic_operations/model/delete.py
orm_core/basic_operations/model/edit.py
orm_core/basic_operations/model/get_all.py
orm_core/basic_operations/model/get_by.py
orm_core/basic_operations/model/settings.py
orm_core/basic_operations/model_with_schemes/__init__.py
orm_core/basic_operations/model_with_schemes/add.py
orm_core/basic_operations/model_with_schemes/delete.py
orm_core/basic_operations/model_with_schemes/edit.py
orm_core/basic_operations/model_with_schemes/get_all.py
orm_core/basic_operations/model_with_schemes/get_by.py
orm_core-0.0.3.dist-info/licenses/LICENSE
orm_core-0.0.3.dist-info/METADATA
orm_core-0.0.3.dist-info/WHEEL
orm_core-0.0.3.dist-info/top_level.txt
orm_core-0.0.3.dist-info/RECORD
