Metadata-Version: 2.4
Name: orm_core
Version: 0.0.3
Summary: ORM Core Library for FastAPI and SQLAlchemy
Home-page: https://github.com/ErJokeCode/orm_core
Author: Erik Soloviev
Author-email: eriksoloviev@gmail.com
License: MIT
Keywords: sqlalchemy fastapi orm pydantic
Classifier: Programming Language :: Python :: 3
Classifier: License :: OSI Approved :: MIT License
Classifier: Operating System :: OS Independent
Requires-Python: >=3.10
License-File: LICENSE
Requires-Dist: pydantic>=2.11.4
Requires-Dist: fastapi>=0.115.12
Requires-Dist: SQLAlchemy>=2.0.41
Requires-Dist: asyncpg==0.30.0
Dynamic: author
Dynamic: author-email
Dynamic: classifier
Dynamic: description
Dynamic: description-content-type
Dynamic: home-page
Dynamic: keywords
Dynamic: license
Dynamic: license-file
Dynamic: requires-dist
Dynamic: requires-python
Dynamic: summary
